{
  "race_info": {
    "race_name": "第 5 場 - 夏佳理錦標（讓賽）",
    "race_date": "2025年7月5日",
    "race_day": "星期六",
    "venue": "沙田",
    "race_time": "18:00",
    "track_type": "草地",
    "course": "C+3",
    "distance": "1200",
    "prize_money": "1,170,000,",
    "rating": "60-40",
    "race_class": "四",
    "full_text": "第 5 場 - 夏佳理錦標（讓賽）2025年7月5日, 星期六, 沙田, 18:00草地, \"C+3\" 賽道, 1200米, 好地獎金: $1,170,000, 評分: 60-40, 第四班"
  },
  "entries": [
    {
      "horse_number": "1",
      "recent_form": "7/1/2/2/6/7",
      "horse_name": "英雄戰歌",
      "horse_code": "J089",
      "weight": "135",
      "jockey": "艾兆禮",
      "draw": "9",
      "trainer": "黎昭昇",
      "rating": "60",
      "rating_change": "0",
      "best_time": "1.09.01",
      "age": "4",
      "season_prize": "1,146,600",
      "days_since_last": "35",
      "equipment": "P-/H/TT",
      "owner": "幸運馬主團體",
      "sire": "Sioux Nation",
      "dam": "Top Classic",
      "import_type": "PPG"
    },
    {
      "horse_number": "2",
      "recent_form": "1",
      "horse_name": "友瑩亮",
      "horse_code": "K400",
      "weight": "134",
      "jockey": "黃智弘 (-5)",
      "draw": "11",
      "trainer": "伍鵬志",
      "rating": "59",
      "rating_change": "7",
      "best_time": "1.09.39",
      "age": "3",
      "season_prize": "655,200",
      "days_since_last": "21",
      "equipment": "CP",
      "owner": "胡珮君與楊毅",
      "sire": "Frosted",
      "dam": "Conscious",
      "import_type": "PPG"
    },
    {
      "horse_number": "3",
      "recent_form": "4/8/3/2/4/6",
      "horse_name": "手錶之星",
      "horse_code": "H483",
      "weight": "128",
      "jockey": "霍宏聲",
      "draw": "10",
      "trainer": "廖康銘",
      "rating": "53",
      "rating_change": "-1",
      "best_time": "1.09.18",
      "age": "5",
      "season_prize": "2,100,150",
      "days_since_last": "24",
      "equipment": "",
      "owner": "楊潔怡",
      "sire": "Written Tycoon",
      "dam": "Lady Gracious",
      "import_type": "ISG"
    },
    {
      "horse_number": "4",
      "recent_form": "-",
      "horse_name": "活力精神",
      "horse_code": "K039",
      "weight": "127",
      "jockey": "潘明輝",
      "draw": "2",
      "trainer": "羅富全",
      "rating": "52",
      "rating_change": "-",
      "best_time": "",
      "age": "4",
      "season_prize": "0",
      "days_since_last": "-",
      "equipment": "TT1",
      "owner": "司徒嘉銘",
      "sire": "Ardrossan",
      "dam": "Miss Rule",
      "import_type": "PPG"
    },
    {
      "horse_number": "5",
      "recent_form": "-",
      "horse_name": "熱氣球",
      "horse_code": "K144",
      "weight": "127",
      "jockey": "布文",
      "draw": "1",
      "trainer": "韋達",
      "rating": "52",
      "rating_change": "-",
      "best_time": "",
      "age": "3",
      "season_prize": "0",
      "days_since_last": "-",
      "equipment": "",
      "owner": "張佐治先生及夫人與張兆興",
      "sire": "Headwater",
      "dam": "Money Wanted",
      "import_type": "PPG"
    },
    {
      "horse_number": "6",
      "recent_form": "10",
      "horse_name": "起舞奜奜",
      "horse_code": "K405",
      "weight": "127",
      "jockey": "奧爾民",
      "draw": "6",
      "trainer": "文家良",
      "rating": "52",
      "rating_change": "0",
      "best_time": "1.10.37",
      "age": "3",
      "season_prize": "0",
      "days_since_last": "13",
      "equipment": "CP1",
      "owner": "24/25 文家良練馬師賽馬團體",
      "sire": "Territories",
      "dam": "Escobar",
      "import_type": "PPG"
    },
    {
      "horse_number": "7",
      "recent_form": "12",
      "horse_name": "天比高",
      "horse_code": "K339",
      "weight": "127",
      "jockey": "梁家俊",
      "draw": "8",
      "trainer": "葉楚航",
      "rating": "52",
      "rating_change": "0",
      "best_time": "",
      "age": "3",
      "season_prize": "0",
      "days_since_last": "45",
      "equipment": "",
      "owner": "最愛馬團體",
      "sire": "El Roca",
      "dam": "Daly River",
      "import_type": "PPG"
    },
    {
      "horse_number": "8",
      "recent_form": "6/3/5/4/1/11",
      "horse_name": "辣得金",
      "horse_code": "J087",
      "weight": "124",
      "jockey": "周俊樂 (-2)",
      "draw": "3",
      "trainer": "巫偉傑",
      "rating": "49",
      "rating_change": "-1",
      "best_time": "1.09.03",
      "age": "4",
      "season_prize": "2,094,300",
      "days_since_last": "24",
      "equipment": "H/TT",
      "owner": "黃紋",
      "sire": "Headwater",
      "dam": "Beechal",
      "import_type": "PPG"
    },
    {
      "horse_number": "9",
      "recent_form": "7/6/10",
      "horse_name": "棒棒糖",
      "horse_code": "J503",
      "weight": "123",
      "jockey": "艾道拿",
      "draw": "12",
      "trainer": "方嘉柏",
      "rating": "48",
      "rating_change": "-2",
      "best_time": "1.10.44",
      "age": "3",
      "season_prize": "23,400",
      "days_since_last": "185",
      "equipment": "XB",
      "owner": "凌偉燊與凌兆銘",
      "sire": "Lonhro",
      "dam": "Sabia",
      "import_type": "PPG"
    },
    {
      "horse_number": "10",
      "recent_form": "11/11/12/5/3/8",
      "horse_name": "歡樂飛駒",
      "horse_code": "J496",
      "weight": "121",
      "jockey": "董明朗",
      "draw": "7",
      "trainer": "呂健威",
      "rating": "46",
      "rating_change": "-2",
      "best_time": "1.10.16",
      "age": "3",
      "season_prize": "175,500",
      "days_since_last": "90",
      "equipment": "B-/XB",
      "owner": "周祈銳先生及夫人與周凱欣",
      "sire": "Charm Spirit",
      "dam": "Lips Of An Angel",
      "import_type": "PPG"
    },
    {
      "horse_number": "11",
      "recent_form": "8/9/3/8/8/3",
      "horse_name": "勁者",
      "horse_code": "J523",
      "weight": "120",
      "jockey": "潘頓",
      "draw": "5",
      "trainer": "蔡約翰",
      "rating": "45",
      "rating_change": "-2",
      "best_time": "1.09.50",
      "age": "4",
      "season_prize": "514,800",
      "days_since_last": "35",
      "equipment": "B/TT",
      "owner": "香港會賽馬團體",
      "sire": "Toronado",
      "dam": "Spot On Maggie",
      "import_type": "PPG"
    },
    {
      "horse_number": "12",
      "recent_form": "4/3/6/8/10/6",
      "horse_name": "嘉應駿馬",
      "horse_code": "J439",
      "weight": "119",
      "jockey": "田泰安",
      "draw": "4",
      "trainer": "大衛希斯",
      "rating": "44",
      "rating_change": "-2",
      "best_time": "1.09.50",
      "age": "3",
      "season_prize": "497,250",
      "days_since_last": "13",
      "equipment": "B/TT",
      "owner": "梁錫光",
      "sire": "Blue Point",
      "dam": "Just Discreet",
      "import_type": "PPG"
    }
  ],
  "reserve_horses": [
    {
      "reserve_number": "1",
      "horse_name": "順善寶",
      "weight": "1177",
      "rating": "125",
      "age": "50",
      "recent_form": "3",
      "trainer": "5/8",
      "priority": "沈集成",
      "equipment": "1"
    },
    {
      "reserve_number": "2",
      "horse_name": "風采人生",
      "weight": "1087",
      "rating": "121",
      "age": "46",
      "recent_form": "4",
      "trainer": "4/8/6/8/6/8",
      "priority": "容天鵬",
      "equipment": "1"
    }
  ],
  "equipment_legend": {
    "B": "戴眼罩",
    "BO": "只戴單邊眼罩",
    "CC": "喉托",
    "CP": "羊毛面箍",
    "CO": "戴單邊羊毛面箍",
    "E": "戴耳塞",
    "H": "戴頭罩",
    "P": "戴防沙眼罩",
    "PC": "戴半掩防沙眼罩",
    "PS": "戴單邊半掩防沙眼罩",
    "SB": "戴羊毛額箍",
    "SR": "鼻箍",
    "TT": "綁繫舌帶",
    "V": "戴開縫眼罩",
    "VO": "戴單邊開縫眼罩",
    "XB": "交叉鼻箍",
    "1": "首次",
    "2": "重戴",
    "-": "除去"
  }
}