{
  "race_info": {
    "race_name": "第 2 場 - 卓越領導",
    "race_date": "2025年7月1日",
    "race_day": "星期二",
    "venue": "沙田",
    "race_time": "16:30",
    "track_type": "草地",
    "course": "C",
    "distance": "1000",
    "prize_money": "1,170,000,",
    "rating": "60-40",
    "race_class": "四",
    "full_text": "第 2 場 - 卓越領導1000米讓賽2025年7月1日, 星期二, 沙田, 16:30草地, \"C\" 賽道, 1000米獎金: $1,170,000, 評分: 60-40, 第四班"
  },
  "entries": [
    {
      "horse_number": "1",
      "recent_form": "9/3/9/5/6/3",
      "horse_name": "英雄豪邁",
      "horse_code": "G394",
      "weight": "135",
      "jockey": "黃智弘 (-5)",
      "draw": "14",
      "trainer": "羅富全",
      "rating": "55",
      "rating_change": "-2",
      "best_time": "0.55.84",
      "age": "6",
      "season_prize": "1,483,050",
      "days_since_last": "6",
      "equipment": "B/TT",
      "owner": "李西廷",
      "sire": "Not A Single Doubt",
      "dam": "Jacquetta",
      "import_type": "PP"
    },
    {
      "horse_number": "2",
      "recent_form": "12/9/9/10/10",
      "horse_name": "萬事得意",
      "horse_code": "K171",
      "weight": "134",
      "jockey": "蔡明紹",
      "draw": "1",
      "trainer": "告東尼",
      "rating": "54",
      "rating_change": "-3",
      "best_time": "",
      "age": "4",
      "season_prize": "0",
      "days_since_last": "34",
      "equipment": "B/TT",
      "owner": "十全勝團體",
      "sire": "Press Statement",
      "dam": "Split The Bill",
      "import_type": "PP"
    },
    {
      "horse_number": "3",
      "recent_form": "2/11/4",
      "horse_name": "團結勇士",
      "horse_code": "K340",
      "weight": "133",
      "jockey": "奧爾民",
      "draw": "4",
      "trainer": "容天鵬",
      "rating": "53",
      "rating_change": "2",
      "best_time": "0.55.94",
      "age": "3",
      "season_prize": "315,900",
      "days_since_last": "23",
      "equipment": "TT",
      "owner": "陳添成與彭慧克",
      "sire": "Hellbent",
      "dam": "Witless",
      "import_type": "PPG"
    },
    {
      "horse_number": "4",
      "recent_form": "-",
      "horse_name": "極炸",
      "horse_code": "K224",
      "weight": "132",
      "jockey": "董明朗",
      "draw": "10",
      "trainer": "蘇偉賢",
      "rating": "52",
      "rating_change": "-",
      "best_time": "",
      "age": "3",
      "season_prize": "0",
      "days_since_last": "-",
      "equipment": "TT1",
      "owner": "王嘉俊",
      "sire": "Toronado",
      "dam": "Persian Princess",
      "import_type": "PPG"
    },
    {
      "horse_number": "5",
      "recent_form": "12",
      "horse_name": "喜行",
      "horse_code": "K399",
      "weight": "132",
      "jockey": "湯普新",
      "draw": "2",
      "trainer": "大衛希斯",
      "rating": "52",
      "rating_change": "0",
      "best_time": "0.57.10",
      "age": "3",
      "season_prize": "0",
      "days_since_last": "23",
      "equipment": "CP/TT",
      "owner": "開心計劃團體",
      "sire": "Deep Field",
      "dam": "Anyaas",
      "import_type": "PPG"
    },
    {
      "horse_number": "6",
      "recent_form": "-",
      "horse_name": "森洺之巔",
      "horse_code": "K430",
      "weight": "132",
      "jockey": "鍾易禮 (-2)",
      "draw": "12",
      "trainer": "葉楚航",
      "rating": "52",
      "rating_change": "-",
      "best_time": "",
      "age": "3",
      "season_prize": "0",
      "days_since_last": "-",
      "equipment": "B1/TT1",
      "owner": "何沛龍與李頌怡",
      "sire": "Brutal",
      "dam": "Falika",
      "import_type": "PPG"
    },
    {
      "horse_number": "7",
      "recent_form": "-",
      "horse_name": "飛龍在天",
      "horse_code": "K411",
      "weight": "132",
      "jockey": "班德禮",
      "draw": "7",
      "trainer": "方嘉柏",
      "rating": "52",
      "rating_change": "-",
      "best_time": "",
      "age": "3",
      "season_prize": "0",
      "days_since_last": "-",
      "equipment": "",
      "owner": "黃楚標",
      "sire": "All Too Hard",
      "dam": "Piazza del Campo",
      "import_type": "PPG"
    },
    {
      "horse_number": "8",
      "recent_form": "-",
      "horse_name": "官金騏",
      "horse_code": "K485",
      "weight": "132",
      "jockey": "潘頓",
      "draw": "13",
      "trainer": "文家良",
      "rating": "52",
      "rating_change": "-",
      "best_time": "",
      "age": "3",
      "season_prize": "0",
      "days_since_last": "-",
      "equipment": "",
      "owner": "郭明莉",
      "sire": "Hellbent",
      "dam": "Silent Rage",
      "import_type": "PPG"
    },
    {
      "horse_number": "9",
      "recent_form": "-",
      "horse_name": "巴閉佬",
      "horse_code": "K323",
      "weight": "132",
      "jockey": "艾兆禮",
      "draw": "9",
      "trainer": "呂健威",
      "rating": "52",
      "rating_change": "-",
      "best_time": "",
      "age": "3",
      "season_prize": "0",
      "days_since_last": "-",
      "equipment": "",
      "owner": "麥啟聰",
      "sire": "Magna Grecia",
      "dam": "Cat's Wish",
      "import_type": "PPG"
    },
    {
      "horse_number": "10",
      "recent_form": "8/6/2/9/5/11",
      "horse_name": "凝聚美麗",
      "horse_code": "J299",
      "weight": "131",
      "jockey": "巴度",
      "draw": "8",
      "trainer": "巫偉傑",
      "rating": "51",
      "rating_change": "-2",
      "best_time": "",
      "age": "4",
      "season_prize": "380,250",
      "days_since_last": "27",
      "equipment": "TT",
      "owner": "郭少明",
      "sire": "Night Of Thunder",
      "dam": "Tawayna",
      "import_type": "PP"
    },
    {
      "horse_number": "11",
      "recent_form": "11/13",
      "horse_name": "駿馬之寶",
      "horse_code": "J373",
      "weight": "130",
      "jockey": "梁家俊",
      "draw": "5",
      "trainer": "羅富全",
      "rating": "50",
      "rating_change": "-2",
      "best_time": "",
      "age": "3",
      "season_prize": "0",
      "days_since_last": "34",
      "equipment": "CP",
      "owner": "李逢泰",
      "sire": "Cosmic Force",
      "dam": "Quick's The Word",
      "import_type": "PPG"
    },
    {
      "horse_number": "12",
      "recent_form": "9/6/4",
      "horse_name": "金滙千帥",
      "horse_code": "J498",
      "weight": "128",
      "jockey": "艾道拿",
      "draw": "6",
      "trainer": "賀賢",
      "rating": "48",
      "rating_change": "-2",
      "best_time": "0.57.04",
      "age": "3",
      "season_prize": "93,600",
      "days_since_last": "48",
      "equipment": "B",
      "owner": "關偉明與梁錦泉",
      "sire": "Darci Brahma",
      "dam": "Flying Firebird",
      "import_type": "PPG"
    },
    {
      "horse_number": "13",
      "recent_form": "2/11/5/5/9/6",
      "horse_name": "銀河勇士",
      "horse_code": "J238",
      "weight": "124",
      "jockey": "霍宏聲",
      "draw": "3",
      "trainer": "丁冠豪",
      "rating": "44",
      "rating_change": "0",
      "best_time": "0.56.11",
      "age": "4",
      "season_prize": "351,000",
      "days_since_last": "9",
      "equipment": "CP",
      "owner": "吳豐盛",
      "sire": "Swiss Ace",
      "dam": "Funhouse",
      "import_type": "PPG"
    },
    {
      "horse_number": "14",
      "recent_form": "6/6/11/3/12/12",
      "horse_name": "魅力星",
      "horse_code": "K052",
      "weight": "122",
      "jockey": "田泰安",
      "draw": "11",
      "trainer": "蔡約翰",
      "rating": "42",
      "rating_change": "-2",
      "best_time": "0.56.03",
      "age": "3",
      "season_prize": "181,350",
      "days_since_last": "23",
      "equipment": "B/TT",
      "owner": "鄧詠琳",
      "sire": "Toronado",
      "dam": "Big Spirit",
      "import_type": "PPG"
    }
  ],
  "reserve_horses": [
    {
      "reserve_number": "1",
      "horse_name": "辣得金",
      "weight": "",
      "rating": "129",
      "age": "49",
      "recent_form": "4",
      "trainer": "6/3/5/4/1/11",
      "priority": "巫偉傑",
      "equipment": "2"
    },
    {
      "reserve_number": "2",
      "horse_name": "錶之多多",
      "weight": "",
      "rating": "121",
      "age": "41",
      "recent_form": "5",
      "trainer": "6/1/4/2/1/2",
      "priority": "文家良",
      "equipment": "2"
    }
  ],
  "equipment_legend": {
    "B": "戴眼罩",
    "BO": "只戴單邊眼罩",
    "CC": "喉托",
    "CP": "羊毛面箍",
    "CO": "戴單邊羊毛面箍",
    "E": "戴耳塞",
    "H": "戴頭罩",
    "P": "戴防沙眼罩",
    "PC": "戴半掩防沙眼罩",
    "PS": "戴單邊半掩防沙眼罩",
    "SB": "戴羊毛額箍",
    "SR": "鼻箍",
    "TT": "綁繫舌帶",
    "V": "戴開縫眼罩",
    "VO": "戴單邊開縫眼罩",
    "XB": "交叉鼻箍",
    "1": "首次",
    "2": "重戴",
    "-": "除去"
  }
}